{
  "Version": "2012-10-17",
  "Statement": [
    {
      "Sid": "AllowS3Artifacts",
      "Effect": "Allow",
      "Action": ["s3:GetObject", "s3:PutObject", "s3:ListBucket"],
      "Resource": [
        "arn:aws:s3:::${ARTIFACTS_BUCKET}",
        "arn:aws:s3:::${ARTIFACTS_BUCKET}/*"
      ]
    },
    {
      "Sid": "AllowCodeBuild",
      "Effect": "Allow",
      "Action": [
        "codebuild:StartBuild",
        "codebuild:BatchGetBuilds",
        "codebuild:BatchGetProjects"
      ],
      "Resource": "*"
    },
    {
      "Sid": "CloudWatchLogs",
      "Effect": "Allow",
      "Action": ["logs:CreateLogStream", "logs:PutLogEvents"],
      "Resource": "*"
    }
  ]
}
